fluentes/__init__.py
fluentes/examples.py
fluentes/query_builder.py
fluentes-0.1.0.dist-info/licenses/LICENSE
fluentes-0.1.0.dist-info/METADATA
fluentes-0.1.0.dist-info/WHEEL
fluentes-0.1.0.dist-info/top_level.txt
fluentes-0.1.0.dist-info/RECORD
