Metadata-Version: 2.4
Name: fluentes
Version: 0.1.0
Summary: A fluent API for Elasticsearch operations
Author-email: Shahram Saghaei <shahram4dev@gmail.com>
License: MIT License
Project-URL: Homepage, https://github.com/bio-informatician/FluentES
Project-URL: Issues, https://github.com/bio-informatician/FluentES/issues
Requires-Python: >=3.8
License-File: LICENSE
Requires-Dist: elasticsearch>=8.0
Dynamic: license-file
